setup.py
grt/GerritClient.py
grt/__init__.py
grt/grt
grt/scp.py
grt.egg-info/PKG-INFO
grt.egg-info/SOURCES.txt
grt.egg-info/dependency_links.txt
grt.egg-info/requires.txt
grt.egg-info/top_level.txt
grt/commands/__init__.py
grt/commands/clone.py
grt/commands/ls_projects.py