Metadata-Version: 1.1
Name: grt
Version: 0.1
Summary: Gerrit Git Repository Helper
Home-page: http://guildencrantz.github.com/grt/
Author: Matt Henkel
Author-email: matt@menagerie.cc
License: UNKNOWN
Platform: UNKNOWN
Classifier: Development Status :: 3 - Alpha
Classifier: Environment :: Console
Classifier: Intended Audience :: Developers
Classifier: License :: OSI Approved :: Apache Software License
